ringba_api_client/__init__.py
ringba_api_client/ringba_api_client.py
ringba_api_client-0.0.1.dist-info/LICENSE.rst
ringba_api_client-0.0.1.dist-info/WHEEL
ringba_api_client-0.0.1.dist-info/METADATA
ringba_api_client-0.0.1.dist-info/RECORD
