Metadata-Version: 2.1
Name: ringba-api-client
Version: 0.0.1
Summary: Simple Rrequest package to integrate with the Ringba Public API
Home-page: https://github.com/nat5142/ringba-api-client
Keywords: ringba-api-client
Author: Nick Tulli
Author-email: ntulli.dev@gmail.com
Requires-Python: >=3.8,<3.12
Classifier: Development Status :: 2 - Pre-Alpha
Classifier: Intended Audience :: Developers
Classifier: License :: OSI Approved :: MIT License
Classifier: Natural Language :: English
Classifier: Programming Language :: Python :: 3
Classifier: Programming Language :: Python :: 3.8
Classifier: Programming Language :: Python :: 3.9
Classifier: Programming Language :: Python :: 3.10
Classifier: Programming Language :: Python :: 3.11
Classifier: Programming Language :: Python :: 3
Classifier: Programming Language :: Python :: 3.10
Classifier: Programming Language :: Python :: 3.11
Classifier: Programming Language :: Python :: 3.8
Classifier: Programming Language :: Python :: 3.9
Requires-Dist: rest-wrapper (==0.0.2)
Project-URL: Bug Tracker, https://github.com/nat5142/ringba-api-client/issues
Project-URL: Documentation, https://ringba-api-client.readthedocs.io
Project-URL: Repository, https://github.com/nat5142/ringba-api-client
